shxparser/__init__.py
shxparser/shxparser.py
test/__init__.py
test/test_parser.py
shxparser-0.0.2.dist-info/LICENSE
shxparser-0.0.2.dist-info/METADATA
shxparser-0.0.2.dist-info/WHEEL
shxparser-0.0.2.dist-info/top_level.txt
shxparser-0.0.2.dist-info/zip-safe
shxparser-0.0.2.dist-info/RECORD
