Metadata-Version: 2.1
Name: shxparser
Version: 0.0.2
Summary: SHX Line Font Parser
Home-page: https://github.com/tatarize/shxparser
Author: Tatarize
Author-email: tatarize@gmail.com
License: MIT
Keywords: hershey fonts,line fonts,vectors,shx
Platform: UNKNOWN
Classifier: Development Status :: 4 - Beta
Classifier: Intended Audience :: Developers
Classifier: License :: OSI Approved :: MIT License
Classifier: Operating System :: OS Independent
Classifier: Programming Language :: Python
Classifier: Programming Language :: Python :: 3.6
Classifier: Programming Language :: Python :: 3.7
Classifier: Programming Language :: Python :: 3.8
Classifier: Programming Language :: Python :: 3.9
Classifier: Programming Language :: Python :: 3.10
Classifier: Programming Language :: Python :: Implementation :: PyPy
Classifier: Topic :: Multimedia :: Graphics :: Editors :: Vector-Based
Classifier: Topic :: Software Development :: Libraries :: Python Modules
Classifier: Topic :: Utilities
